rsfile/__init__.py
rsfile/rsfile_definitions.py
rsfile/rsfile_factories.py
rsfile/rsfile_registries.py
rsfile/rsfile_streams.py
rsfile/rsfile_utilities.py
rsfile/rsfileio_abstract.py
rsfile/rsfileio_unix.py
rsfile/rsfileio_windows.py
rsfile/rsiobase.py
rsfile/rsbackend/__init__.py
rsfile/rsbackend/_utilities.py
rsfile/rsbackend/raw_unix_defines.py
rsfile/rsbackend/raw_win32_ctypes.py
rsfile/rsbackend/raw_win32_defines.py
rsfile/rsbackend/unix_stdlib.py
rsfile/rsbackend/windows_ctypes.py
rsfile/rsbackend/windows_pywin32.py
rsfile/rstest/__init__.py
rsfile/rstest/_fd_inheritance_tester.py
rsfile/rstest/_utilities.py
rsfile/rstest/_worker_process.py
rsfile/rstest/run_iobench.py
rsfile/rstest/test_backend_utilities.py
rsfile/rstest/test_rsfile_locking.py
rsfile/rstest/test_rsfile_retrocompatibility.py
rsfile/rstest/test_rsfile_stdlib.py
rsfile/rstest/test_rsfile_streams.py
rsfile/rstest/stdlib/__init__.py
rsfile/rstest/stdlib/_pyio_py27_backup.py
rsfile/rstest/stdlib/_pyio_py310_backup.py
rsfile/rstest/stdlib/_pyio_py311_backup.py
rsfile/rstest/stdlib/_pyio_py312_backup.py
rsfile/rstest/stdlib/_pyio_py313_backup.py
rsfile/rstest/stdlib/_pyio_py34_backup.py
rsfile/rstest/stdlib/_pyio_py35_backup.py
rsfile/rstest/stdlib/_pyio_py36_backup.py
rsfile/rstest/stdlib/_pyio_py37_backup.py
rsfile/rstest/stdlib/_pyio_py38_backup.py
rsfile/rstest/stdlib/_pyio_py39_backup.py
rsfile/rstest/stdlib/iobench.py
rsfile/rstest/stdlib/test_io_py311.py
rsfile/rstest/stdlib/test_io_py312.py
rsfile-3.3.dist-info/licenses/License.txt
rsfile-3.3.dist-info/METADATA
rsfile-3.3.dist-info/WHEEL
rsfile-3.3.dist-info/top_level.txt
rsfile-3.3.dist-info/RECORD
